{
  "course_code": "PSY 2220",
  "course_title": "Adult Development and Aging",
  "credits": "3",
  "description": "Offered: annually\nThis course examines the developmental changes that occur in early adulthood, middle adulthood, and in the later part of the life span. The course will also cover death, dying and bereavement. Students will be introduced to the research methods employed in the study of adult development and aging. They will also address theory concerning relevant biological, physiological, cognitive, and psychosocial processes. Finally, the course will cover some of the applications and interventions developed by psychological scientists in this field.\nPrerequisite(s): PSY 1100 or PSY 1200\nMeets General Education Requirement(s): AIA",
  "prerequisites": "PSY 1100 or PSY 1200",
  "source_url": "https://catalog.fitchburgstate.edu/preview_course_nopop.php?catoid=53&coid=102751",
  "scraped_at": "2026-06-10T19:24:22.130179+00:00"
}