{
  "course_code": "GEOG 4110",
  "course_title": "Planetary Science",
  "credits": "3",
  "description": "Offered: every other year\nThis course explores the fundamental characteristics of solar system bodies, including the formation and evolution of their surfaces, interiors and atmospheres. Topics include spacecraft exploration, impact cratering, tectonics, volcanism, climate and the internal structure of planets, satellites, and small bodies.\nPrerequisite(s): MATH 1300 and at least one of the following: GEOG 2100 , GEOG 2200 , PHYS 2300",
  "prerequisites": "MATH 1300 and at least one of the following: GEOG 2100 , GEOG 2200 , PHYS 2300",
  "source_url": "https://catalog.fitchburgstate.edu/preview_course_nopop.php?catoid=53&coid=102133",
  "scraped_at": "2026-06-10T19:11:59.717321+00:00"
}