{
  "course_code": "CMGT 4020",
  "course_title": "Communication and Transportation Technologies",
  "credits": "3",
  "description": "Offered: Spring\nThe course studies communication and transportation systems specifically as they relate to the construction industry. Above and below ground infrastructure development for transportation, traffic management, and communication systems are addressed as part of this course.\nPrerequisite(s): CMGT 3035 , ENGT 2030 , and ENGT 3022",
  "prerequisites": "CMGT 3035 , ENGT 2030 , and ENGT 3022",
  "source_url": "https://catalog.fitchburgstate.edu/preview_course_nopop.php?catoid=53&coid=103033",
  "scraped_at": "2026-06-10T19:30:49.238194+00:00"
}