{
  "course_code": "COMM 3835",
  "course_title": "Client Project Production",
  "credits": "3",
  "description": "Offered: every semester\nThis course provides students with the experience of developing a client project from inception to production to the final hand-off of professional caliber work. Working in small teams, students gain valuable experience in teamwork, group communication, collaborative leadership, and client management as they guide the production process, facilitate weekly meetings with their client, and ultimately complete a real world client project.",
  "prerequisites": "",
  "source_url": "https://catalog.fitchburgstate.edu/preview_course_nopop.php?catoid=53&coid=101795",
  "scraped_at": "2026-06-10T19:03:56.750784+00:00"
}