{
  "course_code": "GEOG 3400",
  "course_title": "Population Geography",
  "credits": "3",
  "description": "Offered: every other year\nThe course addresses population processes and characteristics relative to resources in both economically developed and underdeveloped countries and regions. Course material provides both a systematic and regional view of world population problems.\nMeets General Education Requirement(s): DP",
  "prerequisites": "",
  "source_url": "https://catalog.fitchburgstate.edu/preview_course_nopop.php?catoid=53&coid=102131",
  "scraped_at": "2026-06-10T19:11:55.050516+00:00"
}