{
  "course_code": "GEOG 2100",
  "course_title": "Geology",
  "credits": "3",
  "description": "Offered: every semester\nThe course is an introductory survey of the basic elements of physical and historical geology. The class is open to all students. A laboratory is required.\nPrerequisite(s): Successful completion of the Quantitative Reasoning requirement. GEOG 1000 is strongly suggested.\nMeets General Education Requirement(s): PL, SI",
  "prerequisites": "Successful completion of the Quantitative Reasoning requirement. GEOG 1000 is strongly suggested.",
  "source_url": "https://catalog.fitchburgstate.edu/preview_course_nopop.php?catoid=53&coid=102118",
  "scraped_at": "2026-06-10T19:11:39.522959+00:00"
}