{
  "course_code": "HIST 2141",
  "course_title": "Slavery in the Atlantic World",
  "credits": "3",
  "description": "Offered: every other year\nThe course introduces students to the evolution of slavery and the slave trade in the Atlantic World from its roots in the Mediterranean region and Africa to its transformation in the Caribbean basin as a forerunner of modern industrial production. The approach of the course will be comparative in the sense that students will see how slavery has changed over time, and how it differed from place to place and from plantation to plantation.\nPrerequisite(s): AMST 1800 or ENGL 1200 or HIST 1000 or HIST 1100 or HIST 1400 or HIST 1500\nMeets General Education Requirement(s): AIA, DP, HI",
  "prerequisites": "AMST 1800 or ENGL 1200 or HIST 1000 or HIST 1100 or HIST 1400 or HIST 1500",
  "source_url": "https://catalog.fitchburgstate.edu/preview_course_nopop.php?catoid=53&coid=102185",
  "scraped_at": "2026-06-10T19:13:07.128312+00:00"
}