{
  "course_code": "ENGT 4930",
  "course_title": "Engineering Technology Internship",
  "credits": "3",
  "description": "Offered: Fall\nStudents will acquire their career based professional skills and knowledge through the internship as an off-campus experiential learning activity. They have to get pre-approval from the department/university prior to involve in the internship project on-site to get internship credits.\nPrerequisite(s): Junior status\nMeets General Education Requirement(s): AIA",
  "prerequisites": "Junior status",
  "source_url": "https://catalog.fitchburgstate.edu/preview_course_nopop.php?catoid=53&coid=103134",
  "scraped_at": "2026-06-10T19:32:23.024957+00:00"
}