{
  "course_code": "ENGL 4600",
  "course_title": "Literary Cult of the Virgin Queen",
  "credits": "3",
  "description": "Offered: every fourth semester\nRepresentations of England’s controversial “Virgin Queen” (1558-1603) were central to the nation’s literary, artistic, and cultural life. This course examines key texts about Elizabeth I by contemporary writers and courtiers like Philip Sidney, Edmund Spenser, Walter Ralegh and William Shakespeare, as well as literature by lesser-known male and female writers of the 16th and 17th centuries.\nPrerequisite(s): ENGL 1200 or HON 1200\nMeets General Education Requirement(s): AIA, IHIP, LI",
  "prerequisites": "ENGL 1200 or HON 1200",
  "source_url": "https://catalog.fitchburgstate.edu/preview_course_nopop.php?catoid=53&coid=102045",
  "scraped_at": "2026-06-10T19:10:27.465647+00:00"
}