{
  "course_code": "FREN 2000",
  "course_title": "Intermediate French I",
  "credits": "3",
  "description": "Offered: Fall\nThis course serves as a continuation of FREN 1100 and continues practice in grammar and conversation skills, and includes writing exercises as well as reading on life customs and culture of France and French-speaking nations.\nPrerequisite(s): Two years of high school French or FREN 1100\nMeets General Education Requirement(s): AIA, DP",
  "prerequisites": "Two years of high school French or FREN 1100",
  "source_url": "https://catalog.fitchburgstate.edu/preview_course_nopop.php?catoid=53&coid=102104",
  "scraped_at": "2026-06-10T19:11:21.770103+00:00"
}