{
  "course_code": "ENGT 4903",
  "course_title": "Engineering Technology Capstone",
  "credits": "3",
  "description": "Offered: Spring\nStudents apply acquired skills and techniques to a specific project relative to their concentration of study. The project identifies a real-world engineering technology problem, issue, event, developing technology, or case study to which the student will research, exploring, evaluate, and theorize a solution in a final paper and project/presentation format.\nPrerequisite(s): ENGT 4700",
  "prerequisites": "ENGT 4700",
  "source_url": "https://catalog.fitchburgstate.edu/preview_course_nopop.php?catoid=53&coid=103022",
  "scraped_at": "2026-06-10T19:30:30.841224+00:00"
}