{
  "course_code": "SOC 3500",
  "course_title": "Law and Society",
  "credits": "3",
  "description": "Offered: every other year\nThis course focuses on law as a practical resource. Students examine how the availability of law is distributed in society, what the law provides for those who use it, and how the law has been influenced by certain trends of use. Students study ways in which the law has been analyzed and discover the nature of legal evolution and social change.\nPrerequisite(s): SOC 1100\nMeets General Education Requirement(s): CV, DP",
  "prerequisites": "SOC 1100",
  "source_url": "https://catalog.fitchburgstate.edu/preview_course_nopop.php?catoid=53&coid=102609",
  "scraped_at": "2026-06-10T19:21:02.730002+00:00"
}