{
  "course_code": "CJ 3000",
  "course_title": "Domestic Terrorism and Hate Crime",
  "credits": "3",
  "description": "Offered: every other year\nFrom the Ku Klux Klan to Timothy McVeigh, a few Americans have sought to achieve their ends through violent action. This course introduces students to the variety of extremist groups within the United States and examines their history, nature, extent and dangerousness. It also explores hate crime, a relatively new responsibility of the criminal justice system. We will look at the social construction of hate crime and issues concerning its enforcement.\nPrerequisite(s): CJ 1000",
  "prerequisites": "CJ 1000",
  "source_url": "https://catalog.fitchburgstate.edu/preview_course_nopop.php?catoid=53&coid=101898",
  "scraped_at": "2026-06-10T19:06:20.696115+00:00"
}